oakley/__init__.py
oakley/fancy_context_manager.py
oakley/fancy_string.py
oakley/message.py
oakley/mutable_class.py
oakley/print_stack.py
oakley/progress_bar.py
oakley/status.py
oakley/task.py
oakley/xconfig.py
oakley-2.1.13.dist-info/licenses/LICENSE
oakley-2.1.13.dist-info/METADATA
oakley-2.1.13.dist-info/WHEEL
oakley-2.1.13.dist-info/top_level.txt
oakley-2.1.13.dist-info/RECORD
