Metadata-Version: 2.4
Name: oakley
Version: 2.1.13
Summary: A small collection of lightweight, opinionated utilities for printing fancy console output in Python: colored strings, pretty messages, simple progress bars, task context managers, and tiny system/status helpers.
Author-email: Jonas Wehrung-Montpezat <kiwi.grodoudou@gmail.com>
License: MIT
Project-URL: Homepage, https://github.com/ProfesseurShadoko/oakley
Keywords: console,progress bar,utilities,colored output
Requires-Python: >=3.8
License-File: LICENSE
Requires-Dist: psutil>=5.9
Dynamic: license-file
